frigg_runner/__init__.py
frigg_runner/cli.py
frigg_runner/runner.py
frigg_runner/utils.py
frigg_runner-1.2.1.dist-info/DESCRIPTION.rst
frigg_runner-1.2.1.dist-info/METADATA
frigg_runner-1.2.1.dist-info/RECORD
frigg_runner-1.2.1.dist-info/WHEEL
frigg_runner-1.2.1.dist-info/entry_points.txt
frigg_runner-1.2.1.dist-info/metadata.json
frigg_runner-1.2.1.dist-info/top_level.txt
tests/__init__.py
tests/test_cli.py
tests/test_runner.py
tests/test_utils.py
