Metadata-Version: 2.0
Name: frigg-runner
Version: 1.2.1
Summary: Frigg runner execute .frigg.yml file localy.
Home-page: https://github.com/frigg/frigg-runner
Author: The frigg team
Author-email: hi@frigg.io
License: MIT
Keywords: frigg-runner
Platform: UNKNOWN
Classifier: Intended Audience :: Developers
Classifier: License :: OSI Approved :: MIT License
Classifier: Natural Language :: English
Classifier: Programming Language :: Python :: 2
Classifier: Programming Language :: Python :: 2.7
Classifier: Programming Language :: Python :: 3
Classifier: Programming Language :: Python :: 3.4
Requires-Dist: click (==4.1)
Requires-Dist: frigg-coverage (>=1.1.0,<2.0.0)
Requires-Dist: frigg-settings (>=1.0.1,<2.0.0)
Requires-Dist: invoke (==0.10.1)
